HISTORY.rst
LICENSE
MANIFEST.in
README.rst
setup.py
python_tumblpy.egg-info/PKG-INFO
python_tumblpy.egg-info/SOURCES.txt
python_tumblpy.egg-info/dependency_links.txt
python_tumblpy.egg-info/requires.txt
python_tumblpy.egg-info/top_level.txt
tumblpy/__init__.py
tumblpy/api.py
tumblpy/compat.py
tumblpy/exceptions.py
tumblpy/helpers.py