Metadata-Version: 1.0
Name: python-tumblpy
Version: 1.0.1
Summary: A Python Library to interface with Tumblr v2 REST API & OAuth
Home-page: https://github.com/michaelhelmick/python-tumblpy/
Author: Mike Helmick
Author-email: mikehelmick@me.com
License: Copyright (c) 2013, Mike Helmick
